spectrai/__init__.py
spectrai/apply.py
spectrai/evaluate.py
spectrai/initialise.py
spectrai/preview.py
spectrai/previewer.py
spectrai/train.py
spectrai/trainer.py
spectrai/dataloader/__init__.py
spectrai/dataloader/dataloaders.py
spectrai/dataloader/spectral_dataset.py
spectrai/networks/__init__.py
spectrai/networks/layer_utils.py
spectrai/networks/layers.py
spectrai/networks/networks.py
spectrai/networks/nets/__init__.py
spectrai/networks/nets/densenet.py
spectrai/networks/nets/efficientnet.py
spectrai/networks/nets/rcan.py
spectrai/networks/nets/resnet.py
spectrai/networks/nets/segnet.py
spectrai/networks/nets/unet.py
spectrai/transforms/__init__.py
spectrai/transforms/spectral_transforms.py
spectrai/utils/__init__.py
spectrai/utils/utilities.py
spectrai-0.1.4.dist-info/METADATA
spectrai-0.1.4.dist-info/WHEEL
spectrai-0.1.4.dist-info/entry_points.txt
spectrai-0.1.4.dist-info/top_level.txt
spectrai-0.1.4.dist-info/RECORD
