Metadata-Version: 2.1
Name: spectrai
Version: 0.1.4
Summary: spectrai: a deep learning framework for spectral data.
Home-page: https://github.com/conor-horgan/spectrai
Author: Conor Horgan
Author-email: conor.horgan@kcl.ac.uk
License: Apache 2.0
Keywords: spectrai
Classifier: Development Status :: 2 - Pre-Alpha
Classifier: Intended Audience :: Science/Research
Classifier: License :: OSI Approved :: Apache Software License
Classifier: Natural Language :: English
Classifier: Operating System :: OS Independent
Classifier: Programming Language :: Python :: 3.8
Requires-Python: >=3.6, <3.9
Requires-Dist: numpy (==1.23.3)
Requires-Dist: scipy (==1.9.1)
Requires-Dist: torch (>=1.11.0)
Requires-Dist: torchvision (>=0.12.0)
Requires-Dist: tensorboard (==2.10.0)
Requires-Dist: pandas (==1.4.4)
Requires-Dist: scikit-learn (==1.1.2)
Requires-Dist: scikit-image (==0.19.3)
Requires-Dist: Pillow (==9.2.0)
Requires-Dist: PyYAML (==6.0)
